friend_or_foe/__init__.py
friend_or_foe/cli.py
friend_or_foe/test.py
friend_or_foe/data/loader.py
friend_or_foe/model/base.py
friend_or_foe/model/tabm/__init__.py
friend_or_foe/model/tabm/main.py
friend_or_foe/model/tabm/model.py
friend_or_foe-1.0.1.dist-info/LICENSE
friend_or_foe-1.0.1.dist-info/METADATA
friend_or_foe-1.0.1.dist-info/WHEEL
friend_or_foe-1.0.1.dist-info/entry_points.txt
friend_or_foe-1.0.1.dist-info/top_level.txt
friend_or_foe-1.0.1.dist-info/RECORD
