Metadata-Version: 2.2
Name: friend-or-foe
Version: 1.0.1
Summary: A collection of microbial datasets obtained from metabolic modeling for machine learning research
Home-page: https://github.com/powidla/Friend-Or-Foe
Author-email: powidla <poowidla123@gmail.com>
Maintainer-email: powidla <poowidla123@gmail.com>
License:                                  Apache License
Project-URL: Homepage, https://github.com/powidla/Friend-Or-Foe
Project-URL: Documentation, https://elibbylab.github.io/Friend-Or-Foe/
Project-URL: Repository, https://github.com/powidla/Friend-Or-Foe
Project-URL: Bug Tracker, https://github.com/powidla/Friend-Or-Foe/issues
Project-URL: Data Repository, https://huggingface.co/datasets/powidla/Friend-Or-Foe
Keywords: microbiology,machine-learning,metabolic-modeling,bioinformatics,datasets
Classifier: Development Status :: 4 - Beta
Classifier: Intended Audience :: Science/Research
Classifier: License :: OSI Approved :: Apache Software License
Classifier: Operating System :: OS Independent
Classifier: Programming Language :: Python :: 3
Classifier: Programming Language :: Python :: 3.9
Classifier: Programming Language :: Python :: 3.10
Classifier: Programming Language :: Python :: 3.11
Classifier: Programming Language :: Python :: 3.12
Classifier: Topic :: Software Development :: Libraries :: Python Modules
Requires-Python: >=3.8
License-File: LICENSE
Requires-Dist: tqdm==4.67.1
Requires-Dist: rtdl-num-embeddings>=0.0.11
Requires-Dist: scikit-learn==1.6.1
Requires-Dist: scipy==1.15.2
Requires-Dist: pandas==2.2.3
Requires-Dist: numpy==2.1.2
Requires-Dist: matplotlib==3.10.1
Requires-Dist: requests==2.32.3
Requires-Dist: pytorch-tabnet==4.1.0
Requires-Dist: huggingface_hub>=0.20.0
Requires-Dist: delu>=0.0.26
Requires-Dist: rtdl_revisiting_models>=0.0.2
Requires-Dist: shap>=0.41.0
Provides-Extra: dev
Requires-Dist: pytest>=7.0.0; extra == "dev"
Requires-Dist: pytest-cov>=4.0.0; extra == "dev"
Requires-Dist: black>=23.0.0; extra == "dev"
Requires-Dist: flake8>=6.0.0; extra == "dev"
Requires-Dist: isort>=5.12.0; extra == "dev"
Requires-Dist: mypy>=1.0.0; extra == "dev"
Provides-Extra: docs
Requires-Dist: sphinx>=6.0.0; extra == "docs"
Requires-Dist: sphinx-rtd-theme>=1.2.0; extra == "docs"
Requires-Dist: nbsphinx>=0.9.0; extra == "docs"
Provides-Extra: jupyter
Requires-Dist: jupyter>=1.0.0; extra == "jupyter"
Requires-Dist: ipykernel>=6.0.0; extra == "jupyter"
Requires-Dist: notebook>=6.5.0; extra == "jupyter"
Provides-Extra: all
Requires-Dist: friend-or-foe[dev,docs,jupyter]; extra == "all"
Dynamic: home-page
Dynamic: requires-python
